pytapable/__init__.py
pytapable/functional.py
pytapable/hooks.py
pytapable/inline.py
pytapable/intercept_base.py
pytapable/version.py
PyTapable-0.1.0.dist-info/LICENSE
PyTapable-0.1.0.dist-info/METADATA
PyTapable-0.1.0.dist-info/WHEEL
PyTapable-0.1.0.dist-info/top_level.txt
PyTapable-0.1.0.dist-info/RECORD
